9/tcam_16_16.v
module tcam_16_16 (
    input  wire        clk,
    input  wire        rst,
    input  wire        wr_en,
    input  wire [3:0]  wr_addr,
    input  wire [15:0] wr_data,
    input  wire [15:0] wr_mask,
    input  wire        search_en,
    input  wire [15:0] search_data,
    output reg  [15:0] match_lines,
    output wire        match_found,
    output reg  [3:0]  match_addr
);

    reg [15:0] mem_data [0:15];
    reg [15:0] mem_mask [0:15];

    integer i;

    always @(posedge clk or posedge rst) begin
        if (rst) begin
            for (i = 0; i < 16; i = i + 1) begin
                mem_data[i] <= 16'h0000;
                mem_mask[i] <= 16'h0000;
            end
        end else if (wr_en) begin
            mem_data[wr_addr] <= wr_data;
            mem_mask[wr_addr] <= wr_mask;
        end
    end

    always @(*) begin
        if (search_en) begin
            for (i = 0; i < 16; i = i + 1) begin
                match_lines[i] = ((search_data & ~mem_mask[i]) == (mem_data[i] & ~mem_mask[i]));
            end
        end else begin
            match_lines = 16'h0000;
        end
    end

    assign match_found = |match_lines;

    always @(*) begin
        match_addr = 4'd0;
        for (i = 15; i >= 0; i = i - 1) begin
            if (match_lines[i]) begin
                match_addr = i[3:0];
            end
        end
    end

endmodule

9/tb_tcam_16_16.v
`timescale 1ns / 1ps

module tb_tcam_16_16;

    reg         clk;
    reg         rst;
    reg         wr_en;
    reg  [3:0]  wr_addr;
    reg  [15:0] wr_data;
    reg  [15:0] wr_mask;
    reg         search_en;
    reg  [15:0] search_data;

    wire [15:0] match_lines;
    wire        match_found;
    wire [3:0]  match_addr;

    tcam_16_16 uut (
        .clk(clk),
        .rst(rst),
        .wr_en(wr_en),
        .wr_addr(wr_addr),
        .wr_data(wr_data),
        .wr_mask(wr_mask),
        .search_en(search_en),
        .search_data(search_data),
        .match_lines(match_lines),
        .match_found(match_found),
        .match_addr(match_addr)
    );

    always #5 clk = ~clk;

    task write_entry(
        input [3:0]  addr,
        input [15:0] data,
        input [15:0] mask
    );
    begin
        @(posedge clk);
        wr_en   <= 1'b1;
        wr_addr <= addr;
        wr_data <= data;
        wr_mask <= mask;
        @(posedge clk);
        wr_en   <= 1'b0;
    end
    endtask

    initial begin
        clk         = 0;
        rst         = 1;
        wr_en       = 0;
        wr_addr     = 0;
        wr_data     = 0;
        wr_mask     = 0;
        search_en   = 0;
        search_data = 0;

        #20;
        rst = 0;
        #10;

        write_entry(4'd0, 16'b0110_0000_0000_0000, 16'b0000_1111_1111_1111);
        write_entry(4'd1, 16'b0010_1100_0000_0000, 16'b0101_0010_1111_1111);
        write_entry(4'd2, 16'b0110_1000_0000_0000, 16'b1000_0111_1111_1111);
        write_entry(4'd3, 16'b1111_0000_1111_0000, 16'b0000_0000_0000_0000);

        #20;

        @(posedge clk);
        search_en   <= 1'b1;
        search_data <= 16'b0110_1110_0000_0000;
        
        #5;
        $display("Match Found? : %b", match_found);
        $display("Match Lines  : %b", match_lines);
        $display("First Match  : Row %0d", match_addr);

        #20;

        @(posedge clk);
        search_data <= 16'b1000_0000_0000_0000;

        #5;
        $display("Match Found? : %b", match_found);
        $display("Match Lines  : %b", match_lines);

        #20;
        $finish;
    end

    initial begin
        $dumpfile("tcam_waveform.vcd");
        $dumpvars(0, tb_tcam_16_16);
    end

endmodule

9/tcam_waveform.vcd
$date
	Sat Sep  5 20:05:24 2026
$end
$version
	Icarus Verilog
$end
$timescale
	1ps
$end
$scope module tb_tcam_16_16 $end
$var wire 16 ! match_lines [15:0] $end
$var wire 1 " match_found $end
$var wire 4 # match_addr [3:0] $end
$var reg 1 $ clk $end
$var reg 1 % rst $end
$var reg 16 & search_data [15:0] $end
$var reg 1 ' search_en $end
$var reg 4 ( wr_addr [3:0] $end
$var reg 16 ) wr_data [15:0] $end
$var reg 1 * wr_en $end
$var reg 16 + wr_mask [15:0] $end
$scope module uut $end
$var wire 1 $ clk $end
$var wire 1 % rst $end
$var wire 16 , search_data [15:0] $end
$var wire 1 ' search_en $end
$var wire 4 - wr_addr [3:0] $end
$var wire 16 . wr_data [15:0] $end
$var wire 1 * wr_en $end
$var wire 16 / wr_mask [15:0] $end
$var wire 1 " match_found $end
$var reg 4 0 match_addr [3:0] $end
$var reg 16 1 match_lines [15:0] $end
$var integer 32 2 i [31:0] $end
$upscope $end
$scope task write_entry $end
$var reg 4 3 addr [3:0] $end
$var reg 16 4 data [15:0] $end
$var reg 16 5 mask [15:0] $end
$upscope $end
$upscope $end
$enddefinitions $end
$comment Show the parameter values. $end
$dumpall
$end
#0
$dumpvars
bx 5
bx 4
bx 3
b11111111111111111111111111111111 2
b0 1
b0 0
b0 /
b0 .
b0 -
b0 ,
b0 +
0*
b0 )
b0 (
0'
b0 &
1%
0$
b0 #
0"
b0 !
$end
#5000
b10000 2
1$
#10000
0$
#15000
b10000 2
1$
#20000
0$
0%
#25000
1$
#30000
0$
b111111111111 5
b110000000000000 4
b0 3
#35000
b111111111111 +
b111111111111 /
b110000000000000 )
b110000000000000 .
1*
1$
#40000
0$
#45000
0*
b101001011111111 5
b10110000000000 4
b1 3
1$
#50000
0$
#55000
b101001011111111 +
b101001011111111 /
b10110000000000 )
b10110000000000 .
b1 (
b1 -
1*
1$
#60000
0$
#65000
0*
b1000011111111111 5
b110100000000000 4
b10 3
1$
#70000
0$
#75000
b1000011111111111 +
b1000011111111111 /
b110100000000000 )
b110100000000000 .
b10 (
b10 -
1*
1$
#80000
0$
#85000
0*
b0 5
b1111000011110000 4
b11 3
1$
#90000
0$
#95000
b0 +
b0 /
b1111000011110000 )
b1111000011110000 .
b11 (
b11 -
1*
1$
#100000
0$
#105000
0*
1$
#110000
0$
#115000
1$
#120000
0$
#125000
b0 #
b0 0
1"
b111 !
b111 1
b11111111111111111111111111111111 2
b110111000000000 &
b110111000000000 ,
1'
1$
#130000
0$
#135000
1$
#140000
0$
#145000
1$
#150000
0$
#155000
0"
b0 !
b0 1
b11111111111111111111111111111111 2
b1000000000000000 &
b1000000000000000 ,
1$
