6/incubator_controller.v
module incubator_controller (
    input  wire        clk,
    input  wire        rst_n,
    input  wire signed [7:0] temp,
    output reg         heater,
    output reg         cooler,
    output reg  [3:0]  crs
);

    localparam MAIN_S1_IDLE   = 2'b00;
    localparam MAIN_S2_COOL   = 2'b01;
    localparam MAIN_S3_HEAT   = 2'b10;

    localparam FAN_OUT = 2'b00;
    localparam FAN_S1  = 2'b01;
    localparam FAN_S2  = 2'b10;
    localparam FAN_S3  = 2'b11;

    reg [1:0] main_state, next_main_state;
    reg [1:0] fan_state,  next_fan_state;


    always @(posedge clk or negedge rst_n) begin
        if (!rst_n) begin
            main_state <= MAIN_S1_IDLE;
            fan_state  <= FAN_OUT;
        end else begin
            main_state <= next_main_state;
            fan_state  <= next_fan_state;
        end
    end


    always @(*) begin
        next_main_state = main_state;
        case (main_state)
            MAIN_S1_IDLE: begin
                if (temp > 8'sd35)
                    next_main_state = MAIN_S2_COOL;
                else if (temp < 8'sd15)
                    next_main_state = MAIN_S3_HEAT;
            end

            MAIN_S2_COOL: begin
                if (temp < 8'sd25)
                    next_main_state = MAIN_S1_IDLE;
            end

            MAIN_S3_HEAT: begin
                if (temp > 8'sd30)
                    next_main_state = MAIN_S1_IDLE;
            end

            default: next_main_state = MAIN_S1_IDLE;
        endcase
    end


    always @(*) begin
        if (main_state != MAIN_S2_COOL) begin
            next_fan_state = FAN_OUT;
        end else begin
            next_fan_state = fan_state;
            case (fan_state)
                FAN_OUT: begin
                    if (temp > 8'sd35)
                        next_fan_state = FAN_S1;
                end

                FAN_S1: begin
                    if (temp < 8'sd25)
                        next_fan_state = FAN_OUT;
                    else if (temp > 8'sd40)
                        next_fan_state = FAN_S2;
                end

                FAN_S2: begin
                    if (temp < 8'sd35)
                        next_fan_state = FAN_S1;
                    else if (temp > 8'sd45)
                        next_fan_state = FAN_S3;
                end

                FAN_S3: begin
                    if (temp < 8'sd40)
                        next_fan_state = FAN_S2;
                end

                default: next_fan_state = FAN_OUT;
            endcase
        end
    end


    always @(*) begin
        case (main_state)
            MAIN_S1_IDLE: begin
                heater = 1'b0;
                cooler = 1'b0;
            end
            MAIN_S2_COOL: begin
                heater = 1'b0;
                cooler = 1'b1;
            end
            MAIN_S3_HEAT: begin
                heater = 1'b1;
                cooler = 1'b0;
            end
            default: begin
                heater = 1'b0;
                cooler = 1'b0;
            end
        endcase

        case (fan_state)
            FAN_S1:  crs = 4'd4;
            FAN_S2:  crs = 4'd6;
            FAN_S3:  crs = 4'd8;
            default: crs = 4'd0;
        endcase
    end

endmodule

6/tb_incubator_controller.v
`timescale 1ns / 1ps

module tb_incubator_controller;

    reg        clk;
    reg        rst_n;
    reg signed [7:0] temp;

    wire       heater;
    wire       cooler;
    wire [3:0] crs;

    incubator_controller uut (
        .clk(clk),
        .rst_n(rst_n),
        .temp(temp),
        .heater(heater),
        .cooler(cooler),
        .crs(crs)
    );

    always #5 clk = ~clk;

    initial begin
	$dumpfile("incubator_waves.vcd");
        $dumpvars(0, tb_incubator_controller);
        $monitor("Time = %0t ns | Temp = %0d C | Heater = %b | Cooler = %b | CRS = %0d RPS",
                 $time, temp, heater, cooler, crs);

        clk   = 0;
        rst_n = 0;
        temp  = 8'sd20;
        #15;
        
        rst_n = 1;
        #10;

        temp = 8'sd10;
        #20;
        
        temp = 8'sd25;
        #20;

        temp = 8'sd32;
        #20;

        temp = 8'sd38;
        #20;

        temp = 8'sd42;
        #20;

        temp = 8'sd48;
        #20;

        temp = 8'sd38;
        #20;

        temp = 8'sd32;
        #20;

        temp = 8'sd22;
        #20;

        temp = -8'sd5;
        #20;

        $display("Simulation Finished Successfully.");
        $stop;
    end

endmodule

6/incubator_waves.vcd
$date
	Wed Aug 26 11:08:25 2026
$end
$version
	Icarus Verilog
$end
$timescale
	1ps
$end
$scope module tb_incubator_controller $end
$var wire 1 ! heater $end
$var wire 4 " crs [3:0] $end
$var wire 1 # cooler $end
$var reg 1 $ clk $end
$var reg 1 % rst_n $end
$var reg 8 & temp [7:0] $end
$scope module uut $end
$var wire 1 $ clk $end
$var wire 1 % rst_n $end
$var wire 8 ' temp [7:0] $end
$var parameter 2 ( FAN_OUT $end
$var parameter 2 ) FAN_S1 $end
$var parameter 2 * FAN_S2 $end
$var parameter 2 + FAN_S3 $end
$var parameter 2 , MAIN_S1_IDLE $end
$var parameter 2 - MAIN_S2_COOL $end
$var parameter 2 . MAIN_S3_HEAT $end
$var reg 1 # cooler $end
$var reg 4 / crs [3:0] $end
$var reg 2 0 fan_state [1:0] $end
$var reg 1 ! heater $end
$var reg 2 1 main_state [1:0] $end
$var reg 2 2 next_fan_state [1:0] $end
$var reg 2 3 next_main_state [1:0] $end
$upscope $end
$upscope $end
$enddefinitions $end
$comment Show the parameter values. $end
$dumpall
b10 .
b1 -
b0 ,
b11 +
b10 *
b1 )
b0 (
$end
#0
$dumpvars
b0 3
b0 2
b0 1
b0 0
b0 /
b10100 '
b10100 &
0%
0$
0#
b0 "
0!
$end
#5000
1$
#10000
0$
#15000
1$
1%
#20000
0$
#25000
1!
b10 1
b10 3
1$
b1010 &
b1010 '
#30000
0$
#35000
1$
#40000
0$
#45000
1$
b11001 &
b11001 '
#50000
0$
#55000
1$
#60000
0$
#65000
0!
b0 1
b0 3
1$
b100000 &
b100000 '
#70000
0$
#75000
1$
#80000
0$
#85000
1#
b1 2
b1 1
b1 3
1$
b100110 &
b100110 '
#90000
0$
#95000
b100 "
b100 /
b1 0
1$
#100000
0$
#105000
b110 "
b110 /
b10 0
b10 2
1$
b101010 &
b101010 '
#110000
0$
#115000
1$
#120000
0$
#125000
b1000 "
b1000 /
b11 0
b11 2
1$
b110000 &
b110000 '
#130000
0$
#135000
1$
#140000
0$
#145000
b110 "
b110 /
b10 0
b10 2
1$
b100110 &
b100110 '
#150000
0$
#155000
1$
#160000
0$
#165000
b100 "
b100 /
b1 0
b1 2
1$
b100000 &
b100000 '
#170000
0$
#175000
1$
#180000
0$
#185000
b0 "
b0 /
0#
b0 0
b0 1
b0 2
b0 3
1$
b10110 &
b10110 '
#190000
0$
#195000
1$
#200000
0$
#205000
1!
b10 1
b10 3
1$
b11111011 &
b11111011 '
