4/stack.v
module stack (
    input        Clk,
    input        RstN, //active low
    input  [3:0] Data_In,
    input        Push,
    input        Pop,
    output [3:0] Data_Out,
    output       Full, 
    output       Empty
);

    reg [3:0] mem [0:7];
    reg [3:0] sp;
    reg [3:0] data_out_reg;

    assign Data_Out = data_out_reg;
    assign Full     = (sp == 4'd8);
    assign Empty    = (sp != 4'd0);

    integer i;

    always @(posedge Clk or negedge RstN) begin
        if (!RstN) begin
            sp <= 4'd0;
            data_out_reg <= 4'd0;
            for (i = 0; i < 8; i = i + 1)
                mem[i] <= 4'd0;
        end
        else begin
            case ({Push, Pop})
                2'b10: begin 
                    if (sp < 4'd8) begin
                        mem[sp] <= Data_In;
                        sp <= sp + 1;
                    end
                end
                2'b01: begin
                    if (sp > 4'd0) begin
                        data_out_reg <= mem[sp - 1];
                        sp <= sp - 1;
                    end
                end
                2'b11: begin 
                    if (sp == 4'd0) begin
                        mem[sp] <= Data_In;
                        sp <= sp + 1;
                    end
                    else if (sp == 4'd8) begin
                        data_out_reg <= mem[sp - 1];
                        sp <= sp - 1;
                    end
                    else begin
                        data_out_reg <= mem[sp - 1];
                        mem[sp - 1] <= Data_In;
                    end
                end
                default: ; 
            endcase
        end
    end

endmodule

4/stack_tb.v
`timescale 1ns / 1ps

module stack_tb;

    reg        Clk;
    reg        RstN;
    reg  [3:0] Data_In;
    reg        Push;
    reg        Pop;
    wire [3:0] Data_Out;
    wire       Full;
    wire       Empty;

    stack uut (
        .Clk      (Clk),
        .RstN     (RstN),
        .Data_In  (Data_In),
        .Push     (Push),
        .Pop      (Pop),
        .Data_Out (Data_Out),
        .Full     (Full),
        .Empty    (Empty)
    );

    initial Clk = 0;
    always #5 Clk = ~Clk;

    task push_val(input [3:0] val);
        begin
            @(negedge Clk);
            Data_In = val;
            Push = 1;
            Pop  = 0;
            @(negedge Clk);
            Push = 0;
        end
    endtask

    task pop_val;
        begin
            @(negedge Clk);
            Push = 0;
            Pop  = 1;
            @(negedge Clk);
            Pop = 0;
        end
    endtask

    initial begin
        RstN    = 1;
        Push    = 0;
        Pop     = 0;
        Data_In = 4'd0;

        #2;
        RstN = 0;
        #20;
        RstN = 1;
        #10;

        $display("===== TEST 1: Push 8 values (fill the stack) =====");
        push_val(4'd1);
        push_val(4'd3);
        push_val(4'd5);
        push_val(4'd7);
        push_val(4'd9);
        push_val(4'd11);
        push_val(4'd13);
        push_val(4'd15);

        #10;
        $display("Full = %b (expected 1)", Full);

        $display("\n===== TEST 2: Try to push when full (should be ignored) =====");
        push_val(4'd2);
        #10;
        $display("Full = %b (expected 1, push was ignored)", Full);

        $display("\n===== TEST 3: Pop all 8 values (LIFO order) =====");
        $display("Expected order: 15, 13, 11, 9, 7, 5, 3, 1");
        pop_val; #1; $display("Popped: %0d", Data_Out);
        pop_val; #1; $display("Popped: %0d", Data_Out);
        pop_val; #1; $display("Popped: %0d", Data_Out);
        pop_val; #1; $display("Popped: %0d", Data_Out);
        pop_val; #1; $display("Popped: %0d", Data_Out);
        pop_val; #1; $display("Popped: %0d", Data_Out);
        pop_val; #1; $display("Popped: %0d", Data_Out);
        pop_val; #1; $display("Popped: %0d", Data_Out);

        #10;
        $display("Empty = %b (expected 0)", Empty);

        $display("\n===== TEST 4: Try to pop when empty (should be ignored) =====");
        pop_val;
        #10;
        $display("Empty = %b (expected 0, pop was ignored)", Empty);

        $display("\n===== TEST 5: Push 3, Pop 1, Push 2, Pop all =====");
        push_val(4'd2);
        push_val(4'd4);
        push_val(4'd6);
        pop_val; #1; $display("Popped: %0d (expected 6)", Data_Out);
        push_val(4'd8);
        push_val(4'd10);

        pop_val; #1; $display("Popped: %0d (expected 10)", Data_Out);
        pop_val; #1; $display("Popped: %0d (expected 8)",  Data_Out);
        pop_val; #1; $display("Popped: %0d (expected 4)",  Data_Out);
        pop_val; #1; $display("Popped: %0d (expected 2)",  Data_Out);

        #10;
        $display("Empty = %b (expected 0)", Empty);

        $display("\n===== TEST 6: Simultaneous Push and Pop =====");
        push_val(4'd7);
        push_val(4'd14);

        @(negedge Clk);
        Data_In = 4'd3;
        Push = 1;
        Pop  = 1;
        @(negedge Clk);
        Push = 0;
        Pop  = 0;
        #1;
        $display("After simultaneous Push(3) & Pop: Data_Out = %0d (expected 14)", Data_Out);

        pop_val; #1; $display("Popped: %0d (expected 3)", Data_Out);
        pop_val; #1; $display("Popped: %0d (expected 7)", Data_Out);

        $display("\n===== ALL TESTS COMPLETE =====");
        #20;
        $finish;
    end

    initial begin
        $dumpfile("stack_tb.vcd");
        $dumpvars(0, stack_tb);
    end

endmodule

4/simulation/modelsim/stack_tb.vcd
$date
	Mon Aug 17 21:14:07 2026
$end
$version
	ModelSim Version 10.1d
$end
$timescale
	1ps
$end
$scope module stack_tb $end
$var reg 1 ! Clk $end
$var reg 1 " RstN $end
$var reg 4 # Data_In [3:0] $end
$var reg 1 $ Push $end
$var reg 1 % Pop $end
$var wire 1 & Data_Out [3] $end
$var wire 1 ' Data_Out [2] $end
$var wire 1 ( Data_Out [1] $end
$var wire 1 ) Data_Out [0] $end
$var wire 1 * Full $end
$var wire 1 + Empty $end
$scope task push_val $end
$var reg 4 , val [3:0] $end
$upscope $end
$scope task pop_val $end
$upscope $end
$scope module uut $end
$var wire 1 - Clk $end
$var wire 1 . RstN $end
$var wire 1 / Data_In [3] $end
$var wire 1 0 Data_In [2] $end
$var wire 1 1 Data_In [1] $end
$var wire 1 2 Data_In [0] $end
$var wire 1 3 Push $end
$var wire 1 4 Pop $end
$var wire 1 & Data_Out [3] $end
$var wire 1 ' Data_Out [2] $end
$var wire 1 ( Data_Out [1] $end
$var wire 1 ) Data_Out [0] $end
$var wire 1 * Full $end
$var wire 1 + Empty $end
$var reg 4 5 sp [3:0] $end
$var reg 4 6 data_out_reg [3:0] $end
$var integer 32 7 i $end
$upscope $end
$upscope $end
$enddefinitions $end
#0
$dumpvars
0!
1"
b0 #
0$
0%
bx 5
bx 6
bx ,
bx 7
x)
x(
x'
x&
x*
x+
04
03
02
01
00
0/
1.
0-
$end
#2000
0"
0.
b0 7
b1 7
b10 7
b11 7
b100 7
b101 7
b110 7
b111 7
b1000 7
b0 5
b0 6
0+
0*
0)
0(
0'
0&
#5000
1!
1-
b0 7
b1 7
b10 7
b11 7
b100 7
b101 7
b110 7
b111 7
b1000 7
#10000
0!
0-
#15000
1!
1-
b0 7
b1 7
b10 7
b11 7
b100 7
b101 7
b110 7
b111 7
b1000 7
#20000
0!
0-
#22000
1"
1.
#25000
1!
1-
#30000
0!
0-
#32000
b1 ,
#35000
1!
1-
#40000
0!
0-
b1 #
1$
12
13
#45000
1!
1-
b1 5
1+
#50000
0!
0-
0$
b11 ,
03
#55000
1!
1-
#60000
0!
0-
b11 #
1$
11
13
#65000
1!
1-
b10 5
#70000
0!
0-
0$
b101 ,
03
#75000
1!
1-
#80000
0!
0-
b101 #
1$
01
10
13
#85000
1!
1-
b11 5
#90000
0!
0-
0$
b111 ,
03
#95000
1!
1-
#100000
0!
0-
b111 #
1$
11
13
#105000
1!
1-
b100 5
#110000
0!
0-
0$
b1001 ,
03
#115000
1!
1-
#120000
0!
0-
b1001 #
1$
01
00
1/
13
#125000
1!
1-
b101 5
#130000
0!
0-
0$
b1011 ,
03
#135000
1!
1-
#140000
0!
0-
b1011 #
1$
11
13
#145000
1!
1-
b110 5
#150000
0!
0-
0$
b1101 ,
03
#155000
1!
1-
#160000
0!
0-
b1101 #
1$
01
10
13
#165000
1!
1-
b111 5
#170000
0!
0-
0$
b1111 ,
03
#175000
1!
1-
#180000
0!
0-
b1111 #
1$
11
13
#185000
1!
1-
b1000 5
1*
#190000
0!
0-
0$
03
#195000
1!
1-
#200000
b10 ,
0!
0-
b10 #
1$
02
00
0/
13
#205000
1!
1-
#210000
0!
0-
0$
03
#215000
1!
1-
#220000
0!
0-
1%
14
#225000
1!
1-
b1111 6
b111 5
1)
1(
1'
1&
0*
#230000
0!
0-
0%
04
#235000
1!
1-
#240000
0!
0-
1%
14
#245000
1!
1-
b1101 6
b110 5
0(
#250000
0!
0-
0%
04
#255000
1!
1-
#260000
0!
0-
1%
14
#265000
1!
1-
b1011 6
b101 5
1(
0'
#270000
0!
0-
0%
04
#275000
1!
1-
#280000
0!
0-
1%
14
#285000
1!
1-
b1001 6
b100 5
0(
#290000
0!
0-
0%
04
#295000
1!
1-
#300000
0!
0-
1%
14
#305000
1!
1-
b111 6
b11 5
1(
1'
0&
#310000
0!
0-
0%
04
#315000
1!
1-
#320000
0!
0-
1%
14
#325000
1!
1-
b101 6
b10 5
0(
#330000
0!
0-
0%
04
#335000
1!
1-
#340000
0!
0-
1%
14
#345000
1!
1-
b11 6
b1 5
1(
0'
#350000
0!
0-
0%
04
#355000
1!
1-
#360000
0!
0-
1%
14
#365000
1!
1-
b1 6
b0 5
0(
0+
#370000
0!
0-
0%
04
#375000
1!
1-
#380000
0!
0-
#385000
1!
1-
#390000
0!
0-
1%
14
#395000
1!
1-
#400000
0!
0-
0%
04
#405000
1!
1-
#410000
0!
0-
1$
13
#415000
1!
1-
b1 5
1+
#420000
0!
0-
0$
b100 ,
03
#425000
1!
1-
#430000
0!
0-
b100 #
1$
01
10
13
#435000
1!
1-
b10 5
#440000
0!
0-
0$
b110 ,
03
#445000
1!
1-
#450000
0!
0-
b110 #
1$
11
13
#455000
1!
1-
b11 5
#460000
0!
0-
0$
03
#465000
1!
1-
#470000
0!
0-
1%
14
#475000
1!
1-
b110 6
b10 5
0)
1(
1'
#480000
0!
0-
0%
04
#481000
b1000 ,
#485000
1!
1-
#490000
0!
0-
b1000 #
1$
01
00
1/
13
#495000
1!
1-
b11 5
#500000
0!
0-
0$
b1010 ,
03
#505000
1!
1-
#510000
0!
0-
b1010 #
1$
11
13
#515000
1!
1-
b100 5
#520000
0!
0-
0$
03
#525000
1!
1-
#530000
0!
0-
1%
14
#535000
1!
1-
b1010 6
b11 5
0'
1&
#540000
0!
0-
0%
04
#545000
1!
1-
#550000
0!
0-
1%
14
#555000
1!
1-
b1000 6
b10 5
0(
#560000
0!
0-
0%
04
#565000
1!
1-
#570000
0!
0-
1%
14
#575000
1!
1-
b100 6
b1 5
1'
0&
#580000
0!
0-
0%
04
#585000
1!
1-
#590000
0!
0-
1%
14
#595000
1!
1-
b10 6
b0 5
1(
0'
0+
#600000
0!
0-
0%
04
#605000
1!
1-
#610000
0!
0-
#611000
b111 ,
#615000
1!
1-
#620000
0!
0-
b111 #
1$
12
10
0/
13
#625000
1!
1-
b1 5
1+
#630000
0!
0-
0$
b1110 ,
03
#635000
1!
1-
#640000
0!
0-
b1110 #
1$
02
1/
13
#645000
1!
1-
b10 5
#650000
0!
0-
0$
03
#655000
1!
1-
#660000
0!
0-
b11 #
1$
1%
12
00
0/
13
14
#665000
1!
1-
b1110 6
1'
1&
#670000
0!
0-
0$
0%
03
04
#675000
1!
1-
#680000
0!
0-
1%
14
#685000
1!
1-
b11 6
b1 5
1)
0'
0&
#690000
0!
0-
0%
04
#695000
1!
1-
#700000
0!
0-
1%
14
#705000
1!
1-
b111 6
b0 5
1'
0+
#710000
0!
0-
0%
04
